ProjectSetup/__init__.py
ProjectSetup/project.py
ProjectSetup-0.1.1.data/scripts/discover.py
ProjectSetup-0.1.1.data/scripts/quickstart.py
ProjectSetup-0.1.1.dist-info/DESCRIPTION.rst
ProjectSetup-0.1.1.dist-info/METADATA
ProjectSetup-0.1.1.dist-info/RECORD
ProjectSetup-0.1.1.dist-info/WHEEL
ProjectSetup-0.1.1.dist-info/metadata.json
ProjectSetup-0.1.1.dist-info/top_level.txt
test/__init__.py
test/test_project.py
