Metadata-Version: 2.0
Name: ProjectSetup
Version: 0.1.1
Summary: describe your project
Home-page: https://github.com/michagrandel/ProjectSetup
Author: Micha Grandel
Author-email: talk@michagrandel.de
License: UNKNOWN
Keywords: p,y,t,h,o,n
Platform: UNKNOWN
Classifier: Development Status :: 1 - Planning
Classifier: License :: OSI Approved :: Apache Software License
Classifier: Programming Language :: Python
Classifier: Programming Language :: Python :: 2
Classifier: Programming Language :: Python :: 2.7
Classifier: Programming Language :: Python :: 3
Classifier: Programming Language :: Python :: 3.5
Classifier: Programming Language :: Python :: 3.6
Classifier: Operating System :: Microsoft
Classifier: Operating System :: Microsoft :: Windows
Classifier: Operating System :: Microsoft :: Windows :: Windows 10
Classifier: Operating System :: Microsoft :: Windows :: Windows 7
Classifier: Operating System :: Microsoft :: Windows :: Windows 8
Classifier: Operating System :: Microsoft :: Windows :: Windows 8.1
Classifier: Operating System :: OS Independent
Classifier: Operating System :: POSIX :: Linux
Classifier: Natural Language :: English
Requires-Dist: alabaster (>=0.7.10)
Requires-Dist: Babel (>=2.5.3)
Requires-Dist: certifi (>=2017.11.5)
Requires-Dist: chardet (>=3.0.4)
Requires-Dist: colorama (>=0.3.9)
Requires-Dist: docutils (>=0.14)
Requires-Dist: idna (>=2.6)
Requires-Dist: imagesize (>=0.7.1)
Requires-Dist: Jinja2 (>=2.10)
Requires-Dist: lxml (>=4.1.1)
Requires-Dist: MarkupSafe (>=1.0)
Requires-Dist: pip (>=9.0.1)
Requires-Dist: Pygments (>=2.2.0)
Requires-Dist: pytz (>=2017.3)
Requires-Dist: requests (>=2.18.4)
Requires-Dist: setuptools (>=38.4.0)
Requires-Dist: six (>=1.11.0)
Requires-Dist: snowballstemmer (>=1.2.1)
Requires-Dist: Sphinx (>=1.6.6)
Requires-Dist: sphinxcontrib-websupport (>=1.0.1)
Requires-Dist: typing (>=3.6.2)
Requires-Dist: urllib3 (>=1.22)
Requires-Dist: wheel (>=0.30.0)
Provides-Extra: dev
Provides-Extra: test
